weather/__init__.py
weather/weather.py
weather_mcp-0.1.1.dist-info/METADATA
weather_mcp-0.1.1.dist-info/WHEEL
weather_mcp-0.1.1.dist-info/RECORD
