Metadata-Version: 2.4
Name: weather-mcp
Version: 0.1.1
Summary: A weather query tool based on MCP (Model Control Protocol)
Project-URL: Repository, https://github.com/yourusername/weather-mcp
Author-email: Your Name <your.email@example.com>
License-Expression: MIT
Keywords: alerts,cli,forecast,mcp,weather
Requires-Python: >=3.11
Requires-Dist: httpx>=0.28.1
Requires-Dist: mcp[cli]>=1.6.0
